romi/__init__.py
romi/battery.py
romi/cablebot.py
romi/camera.py
romi/clock.py
romi/cnc.py
romi/config.py
romi/linearscan.py
romi/motor_controller.py
romi/motors.py
romi/plantscanner-v3.py
romi/plantscanner.py
romi/steering_controller.py
romi/testmoveto.py
romi_apps-0.3.2.dist-info/licenses/LICENSE
romi_apps-0.3.2.dist-info/METADATA
romi_apps-0.3.2.dist-info/WHEEL
romi_apps-0.3.2.dist-info/top_level.txt
romi_apps-0.3.2.dist-info/RECORD
