Metadata-Version: 2.4
Name: romi-apps
Version: 0.3.2
Summary: Python API to communicate with the ROMI apps
Author-email: "Peter Hanappe, Doug Boari" <peter.hanappe@sony.com>
License-Expression: LGPL-2.1
Project-URL: Homepage, https://github.com/romi/romi-apps
Classifier: Programming Language :: Python :: 3
Classifier: Operating System :: OS Independent
Classifier: Intended Audience :: Developers
Classifier: Topic :: Software Development :: Embedded Systems
Requires-Python: >=3.8
License-File: LICENSE
Requires-Dist: rcom
Dynamic: license-file
